{
  "project_info": {
    "project_number": "426679585080",
    "firebase_url": "https://g-parking-314202-default-rtdb.asia-southeast1.firebasedatabase.app",
    "project_id": "g-parking-314202",
    "storage_bucket": "g-parking-314202.appspot.com"
  },
  "client": [
    {
      "client_info": {
        "mobilesdk_app_id": "1:426679585080:android:7f6bf801db4af93f5319cd",
        "android_client_info": {
          "package_name": "com.example.g_parking"
        }
      },
      "oauth_client": [
        {
          "client_id": "426679585080-4gkdqr7bnos6vf7dk711nru8sfj46oq9.apps.googleusercontent.com",
          "client_type": 3
        }
      ],
      "api_key": [
        {
          "current_key": "AIzaSyCnCYNgOGitIYJZFcCyWAwPU6aURrbQUR0"
        }
      ],
      "services": {
        "appinvite_service": {
          "other_platform_oauth_client": [
            {
              "client_id": "426679585080-4gkdqr7bnos6vf7dk711nru8sfj46oq9.apps.googleusercontent.com",
              "client_type": 3
            }
          ]
        }
      }
    }
  ],
  "configuration_version": "1"
}